{
  "MAX_TOKENS_PER_REQUEST": 128000,
  "configurations": [
    {
      "name": "analyzeProjectStructure",
      "model": "meta-llama/llama-4-maverick:free",
      "modelType": "Reasoning"
    },
    {
      "name": "smartFileFilter",
      "model": "meta-llama/llama-4-maverick:free",
      "modelType": "Reasoning"
    },
    {
      "name": "summarizeContent",
      "model": "meta-llama/llama-4-maverick:free",
      "modelType": "Non Reasoning"
    },
    {
      "name": "analyzeCode",
      "model": "meta-llama/llama-4-maverick:free",
      "modelType": "Non Reasoning"
    },
    {
      "name": "analyzeCallHierarchy",
      "model": "meta-llama/llama-4-maverick:free",
      "modelType": "Reasoning"
    },
    {
      "name": "generateSummary",
      "model": "meta-llama/llama-4-maverick:free",
      "modelType": "Non Reasoning"
    }
  ]
}
  